d51_dirsync/__init__.py
d51_dirsync/options.py
d51_dirsync/run.py
d51_dirsync/syncer.py
d51_dirsync/version.py
tests/__init__.py
tests/_base.py
tests/base_tests.py
tests/cmdline.py
tests/diff.py
tests/errors.py
tests/regexfilters.py
tests/sync.py
tests/trees.py
tests/update.py
d51_dirsync-2.2.7.dist-info/LICENSE.txt
d51_dirsync-2.2.7.dist-info/METADATA
d51_dirsync-2.2.7.dist-info/WHEEL
d51_dirsync-2.2.7.dist-info/entry_points.txt
d51_dirsync-2.2.7.dist-info/top_level.txt
d51_dirsync-2.2.7.dist-info/RECORD
