Metadata-Version: 2.1
Name: d51-dirsync
Version: 2.2.7
Summary: Advanced directory tree synchronisation tool
Home-page: https://github.com/MCVSD51/d51_dirsync
Author: Toby Farley
Author-email: toby.farley@d51schools.org
License: UNKNOWN
Keywords: directory,folder,update,synchronisation
Platform: UNKNOWN
Classifier: Programming Language :: Python
Classifier: Programming Language :: Python :: 2
Classifier: Programming Language :: Python :: 3
Classifier: License :: OSI Approved :: MIT License
Classifier: Operating System :: OS Independent
Classifier: Development Status :: 5 - Production/Stable
Classifier: Intended Audience :: Developers
Classifier: Intended Audience :: End Users/Desktop
Classifier: Environment :: Console
Classifier: Topic :: Utilities
Classifier: Topic :: Desktop Environment
Classifier: Topic :: System :: Archiving :: Backup
Classifier: Topic :: System :: Archiving :: Mirroring
License-File: LICENSE.txt
Requires-Dist: six
